{
    "timestamp": "Tue Dec  2 14:46:18 2025",
    "switches": {
        "0000000000000001": {
            "ports": {
                "1": {
                    "total_rx": 4324,
                    "total_tx": 10176,
                    "speed_rx_bps": 0.0,
                    "speed_tx_bps": 77.82
                },
                "2": {
                    "total_rx": 9410,
                    "total_tx": 9384,
                    "speed_rx_bps": 58.36,
                    "speed_tx_bps": 58.36
                }
            },
            "last_seen": "Tue Dec  2 14:44:58 2025"
        },
        "0000000000000002": {
            "ports": {
                "1": {
                    "total_rx": 9384,
                    "total_tx": 9410,
                    "speed_rx_bps": 58.36,
                    "speed_tx_bps": 58.36
                },
                "2": {
                    "total_rx": 4394,
                    "total_tx": 9960,
                    "speed_rx_bps": 0.0,
                    "speed_tx_bps": 58.36
                }
            },
            "last_seen": "Tue Dec  2 14:44:58 2025"
        }
    },
    "links": [
        {
            "src": {
                "dpid": "0000000000000002",
                "port_no": "00000001",
                "hw_addr": "f2:b0:4d:5f:f8:a0",
                "name": "s2-eth1"
            },
            "dst": {
                "dpid": "0000000000000001",
                "port_no": "00000002",
                "hw_addr": "f2:a7:34:81:47:14",
                "name": "s1-eth2"
            }
        },
        {
            "src": {
                "dpid": "0000000000000001",
                "port_no": "00000002",
                "hw_addr": "f2:a7:34:81:47:14",
                "name": "s1-eth2"
            },
            "dst": {
                "dpid": "0000000000000002",
                "port_no": "00000001",
                "hw_addr": "f2:b0:4d:5f:f8:a0",
                "name": "s2-eth1"
            }
        }
    ]
}